elvia/__init__.py
elvia/const.py
elvia/elvia.py
elvia/elvia_schema.py
pyElvia-0.0.10.dist-info/LICENSE
pyElvia-0.0.10.dist-info/METADATA
pyElvia-0.0.10.dist-info/WHEEL
pyElvia-0.0.10.dist-info/top_level.txt
pyElvia-0.0.10.dist-info/RECORD
